qcloud_cos/__init__.py
qcloud_cos/cos_auth.py
qcloud_cos/cos_client.py
qcloud_cos/cos_common.py
qcloud_cos/cos_config.py
qcloud_cos/cos_cred.py
qcloud_cos/cos_err.py
qcloud_cos/cos_op.py
qcloud_cos/cos_params_check.py
qcloud_cos/cos_request.py
qcloud_cos/threadpool.py
qcloud_cos_v4-0.0.25.dist-info/DESCRIPTION.rst
qcloud_cos_v4-0.0.25.dist-info/METADATA
qcloud_cos_v4-0.0.25.dist-info/RECORD
qcloud_cos_v4-0.0.25.dist-info/WHEEL
qcloud_cos_v4-0.0.25.dist-info/metadata.json
qcloud_cos_v4-0.0.25.dist-info/top_level.txt
test/__init__.py
test/test_simple.py
