Metadata-Version: 2.0
Name: qcloud-cos-v4
Version: 0.0.25
Summary: python sdk for tencent qcloud cos v4.0
Home-page: https://www.qcloud.com
Author: liuchang0812
Author-email: liuchang0812@gmail.com
License: MIT License
Platform: UNKNOWN
Requires-Dist: requests
